example_clients/crew_ai_agent.py
uns_mcp/__init__.py
uns_mcp/__main__.py
uns_mcp/custom_http_client.py
uns_mcp/docstring_extras.py
uns_mcp/server.py
uns_mcp/connectors/__init__.py
uns_mcp/connectors/utils.py
uns_mcp/connectors/destination/__init__.py
uns_mcp/connectors/destination/astra.py
uns_mcp/connectors/destination/databricks_vdt.py
uns_mcp/connectors/destination/databricksvolumes.py
uns_mcp/connectors/destination/destination_tool.py
uns_mcp/connectors/destination/mongo.py
uns_mcp/connectors/destination/neo4j.py
uns_mcp/connectors/destination/pinecone.py
uns_mcp/connectors/destination/s3.py
uns_mcp/connectors/destination/weaviate.py
uns_mcp/connectors/external/__init__.py
uns_mcp/connectors/external/firecrawl.py
uns_mcp/connectors/source/__init__.py
uns_mcp/connectors/source/azure.py
uns_mcp/connectors/source/gdrive.py
uns_mcp/connectors/source/onedrive.py
uns_mcp/connectors/source/s3.py
uns_mcp/connectors/source/salesforce.py
uns_mcp/connectors/source/sharepoint.py
uns_mcp/connectors/source/source_tool.py
uns_mcp/connectors/unstructured_api/__init__.py
uns_mcp/connectors/unstructured_api/partition.py
iflow_mcp_unstructured_io_uns_mcp-0.1.7.dist-info/METADATA
iflow_mcp_unstructured_io_uns_mcp-0.1.7.dist-info/WHEEL
iflow_mcp_unstructured_io_uns_mcp-0.1.7.dist-info/entry_points.txt
iflow_mcp_unstructured_io_uns_mcp-0.1.7.dist-info/top_level.txt
iflow_mcp_unstructured_io_uns_mcp-0.1.7.dist-info/RECORD
